AdderModules.v
`timescale 1ns/100ps

module HalfAdder(
	output wire carry, sum, 
	input wire a, b
);
	xor #2 (sum, a, b);
	and #1 (carry, a, b);
endmodule

module FullAdder(
	output carry, sum,
	input a, b, c
);
	HalfAdder h1(carry1_temp, sum_temp, a, b);
	HalfAdder h2(carry2_temp, sum, sum_temp, c);
	or #1 (carry, carry1_temp, carry2_temp);
endmodule

AdderModule_tb.v
`timescale 1ns/100ps

module AdderModule_tb();
	reg a, b, carry_in;
	wire half_carry, half_sum, full_carry, full_sum;

	HalfAdder __h (half_carry, half_sum, a, b);
	FullAdder __f (full_carry, full_sum, a, b, carry_in);

	initial begin
		a = 0;
		b = 0;
		carry_in = 0;

		$dumpfile("AdderModule.vcd");
		$dumpvars(0, AdderModule_tb);

		#80

		$finish;
	end

	always
		#10 a = ~a;

	always
		#20 b = ~b;

	always
		#40 carry_in = ~carry_in;

endmodule

AdderModule.vcd
$date
	Mon Feb 06 13:14:04 2023
$end
$version
	Icarus Verilog
$end
$timescale
	100ps
$end
$scope module AdderModule_tb $end
$var wire 1 ! half_sum $end
$var wire 1 " half_carry $end
$var wire 1 # full_sum $end
$var wire 1 $ full_carry $end
$var reg 1 % a $end
$var reg 1 & b $end
$var reg 1 ' carry_in $end
$scope module __f $end
$var wire 1 % a $end
$var wire 1 & b $end
$var wire 1 ' c $end
$var wire 1 $ carry $end
$var wire 1 ( sum_temp $end
$var wire 1 # sum $end
$var wire 1 ) carry2_temp $end
$var wire 1 * carry1_temp $end
$scope module h1 $end
$var wire 1 % a $end
$var wire 1 & b $end
$var wire 1 * carry $end
$var wire 1 ( sum $end
$upscope $end
$scope module h2 $end
$var wire 1 ( a $end
$var wire 1 ' b $end
$var wire 1 ) carry $end
$var wire 1 # sum $end
$upscope $end
$upscope $end
$scope module __h $end
$var wire 1 % a $end
$var wire 1 & b $end
$var wire 1 " carry $end
$var wire 1 ! sum $end
$upscope $end
$upscope $end
$enddefinitions $end
$comment Show the parameter values. $end
$dumpall
$end
#0
$dumpvars
x*
x)
x(
0'
0&
0%
x$
x#
x"
x!
$end
#10
0"
0)
0*
#20
0$
0!
0(
#40
0#
#100
1%
#120
1(
1!
#140
1#
#200
0%
1&
#300
1%
#310
1*
1"
#320
1$
0(
0!
#340
0#
#400
0%
0&
1'
#410
0*
0"
#420
0$
1#
#500
1%
#520
1(
1!
#530
1)
#540
1$
0#
#600
0%
1&
#700
1%
#710
1*
1"
#720
0(
0!
#730
0)
#740
1#
#800
0%
0&
0'
