CLA.v
`timescale 1ns/1ns

module CLA(sum,carry,C2L,A,B,Cin); 
	input wire [3:0]A;
	input wire [3:0]B;
	input wire Cin;
	output wire[3:0]sum;
	output carry;
	output C2L;

	wire [3:0]p;
	wire [3:0]g;
	and And[3:0](g[3:0],A[3:0],B[3:0]);
	xor Xor[3:0](p[3:0],A[3:0],B[3:0]);
	
	
	wire[3:0]c;
	
	buf(c[0],Cin);
	and(p0c0,p[0],c[0]);
	or(c[1],p0c0,g[0]);
	
	and(p1p0c0,p[1],p[0],c[0]);
	and(p1g0,p[1],g[0]);
	or(c[2],p1p0c0,p1g0,g[1]);
	
	and(p2p1p0c0,p[2],p[1],p[0],c[0]);
	and(p2p1g0,p[2],p[1],g[0]);
	and(p2g1,p[2],g[1]);
	or(c[3],p2p1p0c0,p2p1g0,p2g1,g[2]);
	
	buf(C2L,c[3]);
	
	and(p3p2p1p0c0,p[3],p[2],p[1],p[0],c[0]);
	and(p3p2p1g0,p[3],p[2],p[1],g[0]);
	and(p3p2g1,p[3],p[2],g[1]);
	and(p3g2,p[3],g[2]);
	or(carry,p3p2p1p0c0,p3p2p1g0,p3p2g1,p3g2,g[3]);
	
	xor XOR[3:0](sum,p,c);
	
endmodule


module CLA16_higher(sum,overF,A,B,sub,sign);
	input wire [15:0] A;
	input wire [15:0] B;
	input sub;
	input sign;
	output wire [15:0] sum;
	output overF;
	
	wire[15:0] op3;

	xor XOR_op[15:0](op3,B,sub);
	wire[3:0] carry;
	wire Cin;
	buf(Cin,sub);
	wire[15:0] p;
	wire[15:0] g;
	and And[15:0](g[15:0],A[15:0],op3[15:0]);
	xor XOR[15:0](p[15:0],A[15:0],op3[15:0]);
	
	and(p0I,p[3],p[2],p[1],p[0]);
	and(p1I,p[7],p[6],p[5],p[4]);
	and(p2I,p[11],p[10],p[9],p[8]);
	and(p3I,p[15],p[14],p[13],p[12]);
	
	and(p3p2p1g0,p[3],p[2],p[1],g[0]);
	and(p3p2g1,p[3],p[2],g[1]);
	and(p3g2,p[3],g[2]);
	and(g0I,p3p2p1g0,p3p2g1,p3g2,g[3]);
	
	and(p7p6p5g4,p[7],p[6],p[5],g[4]);
	and(p7p6g5,p[7],p[6],g[5]);
	and(p7g6,p[7],g[6]);
	and(g1I,p7p6p5g4,p7p6g5,p7g6,g[7]);
	
	and(p11p10p9g8,p[11],p[10],p[9],g[8]);
	and(p11p10g9,p[11],p[10],g[9]);
	and(p11g10,p[11],g[10]);
	and(g2I,p11p10p9g8,p11p10g9,p11g10,g[11]);
	
	and(p15p14p13g12,p[15],p[14],p[13],g[12]);
	and(p15p14g13,p[15],p[14],g[13]);
	and(p15g14,p[15],g[14]);
	and(g3I,p15p14p13g12,p15p14g13,p15g14,g[15]);

	and(p0Ic0,p0I,Cin);
	or(carry[0],p0Ic0,g0I);
	
	and(p1Ip0Ic0,p1I,p0I,Cin);
	and(p1Ig0I,p1I,g0I);
	or(carry[1],p1Ip0Ic0,p1Ig0I,g1I);
	
	and(p2Ip1Ip0Ic0,p2I,p1I,p0I,Cin);
	and(p2Ip1Ig0I,p2I,p1I,g0I);
	and(p2Ig1I,p2I,g1I);
	or(carry[2],p2Ip1Ip0Ic0,p2Ip1Ig0I,p2Ig1I,g2I);
	
	and(p3Ip2Ip1Ip0Ic0,p3I,p2I,p1I,p0I,Cin);
	and(p3Ip2Ip1Ig0I,p3I,p2I,p1I,g0I);
	and(p3Ip2Ig1I,p3I,p2I,g1I);
	and(p3Ig2I,p3I,g2I);
	or(carry[3],p3Ip2Ip1Ip0Ic0,p3Ip2Ip1Ig0I,p3Ip2Ig1I,p3Ig2I,g3I);
	
	wire carry2[3:0];
	wire carry2L[3:0];
	
	CLA cla1(sum[3:0],carry2[0],carry2L[0],A[3:0],op3[3:0],Cin);
	CLA cla2(sum[7:4],carry2[1],carry2L[1],A[7:4],op3[7:4],carry[0]);
	CLA cla3(sum[11:8],carry2[2],carry2L[2],A[11:8],op3[11:8],carry[1]);
	CLA cla4(sum[15:12],carry2[3],carry2L[3],A[15:12],op3[15:12],carry[2]);

	wire o1,o2;
    wire x1,x2;
    wire sub_bar;
    not N2(sub_bar,sub);

    buf Buf1 (o1,carry2[3]);
    xor Xor1 (o2, carry2[3], carry2L[3]);

    wire sign_bar;
    not Not1 (sign_bar, sign); 

    wire mint1, mint2;
    and And1 (mint1, sign_bar, o1,sub_bar);
    and And2 (mint2, sign, o2);

    or Or (overF, mint1, mint2);

endmodule

CLA_NoHigher.v
`timescale 1ns/1ns

module CLA_NoHigher(result,OF,operand1,operand2,sub,sign);

    input[15:0] operand1, operand2;
    input sub, sign;
    output[15:0] result;
    output OF;

    wire[15:0] operand2_bar;
    wire[3:0] carries;
    wire[3:0] c2l;

    wire[15:0] operand3;
    xor Xors[15:0] (operand3[15:0], operand2[15:0], sub);

    not Not[15:0] (operand2_bar[15:0], operand2[15:0]);

    CLA c1 (result[3:0], carries[0], c2l[0], operand1[3:0], operand3[3:0], sub);
    CLA c2 (result[7:4], carries[1], c2l[1], operand1[7:4], operand3[7:4], carries[0]);
    CLA c3 (result[11:8], carries[2], c2l[2], operand1[11:8], operand3[11:8], carries[1]);
    CLA c4 (result[15:12], carries[3], c2l[3], operand1[15:12], operand3[15:12], carries[2]);

    wire o1,o2;
    wire x1,x2;
    wire sub_bar;
    not N2(sub_bar,sub);

    buf Buf1 (o1,carries[3]);
    xor Xor1 (o2, carries[3], c2l[3]);

    wire sign_bar;
    not Not1 (sign_bar, sign); 

    wire mint1, mint2;
    and And1 (mint1, sign_bar, o1,sub_bar);
    and And2 (mint2, sign, o2);

    or Or (OF, mint1, mint2);

endmodule

CLA16_tb.v
`timescale 1ns/100ps

module CLA16_tb ();
    
    reg [15:0] A, B;
    reg subtract;   //  equals 1 for subtraction
    reg sign;       // equals 1 for signed
    wire [15:0] res;
    wire ovflow;

    CLA_NoHigher __C (res, ovflow, A, B, subtract, sign);

    initial begin

        // unsigned case 1 no carry
        A = 16'h0123;
        B = 16'h0345;
        subtract = 0;
        sign = 0;

        $dumpfile("CLA16_tb.vcd");
        $dumpvars(0, CLA16_tb);

        #20
        $display("A = %x, B = %x, RESULT = %x, OvFlow = %b", A, B, res, ovflow);
        $display("Ans should be RESULT = 0468, OvFlow = 0\n");


        // unsigned case 2 carry
        A = 16'hF123;
        B = 16'h1345;
        subtract = 0;
        sign = 0;
        #20
        $display("A = %x, B = %x, RESULT = %x, OvFlow = %b", A, B, res, ovflow);
        $display("Ans should be RESULT = 0468, OvFlow = 1\n");

        // unsigned case 3 subtraction
        A = 16'hF123;
        B = 16'h1345;
        subtract = 1;
        sign = 0;
        #20
        $display("A = %x, B = %x, RESULT = %x, OvFlow = %b", A, B, res, ovflow);
        $display("Ans should be RESULT = DDDE, OvFlow = 0\n");

        // signed case 1 no overflow, positive
        A = 16'h0123;
        B = 16'h0345;
        subtract = 0;
        sign = 1;
        #20
        $display("A = %x, B = %x, RESULT = %x, OvFlow = %b", A, B, res, ovflow);
        $display("Ans should be RESULT = 0468, OvFlow = 0\n");

        // signed case 2  overflow, positive
        A = 16'h7123;
        B = 16'h7345;
        subtract = 0;
        sign = 1
        ;
        #20
        $display("A = %x, B = %x, RESULT = %x, OvFlow = %b", A, B, res, ovflow);
        $display("Ans should be RESULT = E468, OvFlow = 1\n");

        // signed case 3 no overflow, negative
        A = 16'hF123;
        B = 16'hF345;
        subtract = 0;
        sign = 1;
        #20
        $display("A = %x, B = %x, RESULT = %x, OvFlow = %b", A, B, res, ovflow);
        $display("Ans should be RESULT = E468, OvFlow = 0\n");

        // signed case 4 overflow, negative
        A = 16'hA123;
        B = 16'hA345;
        subtract = 0;
        sign = 1;
        #20
        $display("A = %x, B = %x, RESULT = %x, OvFlow = %b", A, B, res, ovflow);
        $display("Ans should be RESULT = 4468, OvFlow = 1\n");

        // signed case 5 addition of opposite signs
        A = 16'hF123;
        B = 16'h1345;
        subtract = 0;
        sign = 1;
        #20
        $display("A = %x, B = %x, RESULT = %x, OvFlow = %b", A, B, res, ovflow);
        $display("Ans should be RESULT = 0468, OvFlow = 0\n");

        // signed case 6 subtraction of opposite signs without overflow
        A = 16'h2123;
        B = 16'hF345;
        subtract = 1;
        sign = 1;
        #20
        $display("A = %x, B = %x, RESULT = %x, OvFlow = %b\n", A, B, res, ovflow);
        $display("Ans should be RESULT = 2DDE, OvFlow = 0\n");

        // signed case 7 subtraction of opposite signs with overflow
        A = 16'h7123;
        B = 16'hA345;
        subtract = 1;
        sign = 1;
        #20
        $display("A = %x, B = %x, RESULT = %x, OvFlow = %b\n", A, B, res, ovflow);
        $display("Ans should be RESULT = CDDE, OvFlow = 1\n");

    end

endmodule

CLA16_tb.vcd
$date
	Mon Feb 06 18:08:42 2023
$end
$version
	Icarus Verilog
$end
$timescale
	100ps
$end
$scope module CLA16_tb $end
$var wire 16 ! res [15:0] $end
$var wire 1 " ovflow $end
$var reg 16 # A [15:0] $end
$var reg 16 $ B [15:0] $end
$var reg 1 % sign $end
$var reg 1 & subtract $end
$scope module __C $end
$var wire 1 " OF $end
$var wire 1 ' mint1 $end
$var wire 1 ( mint2 $end
$var wire 1 ) o1 $end
$var wire 1 * o2 $end
$var wire 16 + operand1 [15:0] $end
$var wire 16 , operand2 [15:0] $end
$var wire 16 - operand2_bar [15:0] $end
$var wire 16 . operand3 [15:0] $end
$var wire 1 % sign $end
$var wire 1 / sign_bar $end
$var wire 1 & sub $end
$var wire 1 0 sub_bar $end
$var wire 16 1 result [15:0] $end
$var wire 4 2 carries [3:0] $end
$var wire 4 3 c2l [3:0] $end
$scope module c1 $end
$var wire 4 4 A [3:0] $end
$var wire 4 5 B [3:0] $end
$var wire 1 6 C2L $end
$var wire 1 & Cin $end
$var wire 1 7 carry $end
$var wire 4 8 g [3:0] $end
$var wire 4 9 p [3:0] $end
$var wire 1 : p0c0 $end
$var wire 1 ; p1g0 $end
$var wire 1 < p1p0c0 $end
$var wire 1 = p2g1 $end
$var wire 1 > p2p1g0 $end
$var wire 1 ? p2p1p0c0 $end
$var wire 1 @ p3g2 $end
$var wire 1 A p3p2g1 $end
$var wire 1 B p3p2p1g0 $end
$var wire 1 C p3p2p1p0c0 $end
$var wire 4 D sum [3:0] $end
$var wire 4 E c [3:0] $end
$upscope $end
$scope module c2 $end
$var wire 4 F A [3:0] $end
$var wire 4 G B [3:0] $end
$var wire 1 H C2L $end
$var wire 1 I Cin $end
$var wire 1 J carry $end
$var wire 4 K g [3:0] $end
$var wire 4 L p [3:0] $end
$var wire 1 M p0c0 $end
$var wire 1 N p1g0 $end
$var wire 1 O p1p0c0 $end
$var wire 1 P p2g1 $end
$var wire 1 Q p2p1g0 $end
$var wire 1 R p2p1p0c0 $end
$var wire 1 S p3g2 $end
$var wire 1 T p3p2g1 $end
$var wire 1 U p3p2p1g0 $end
$var wire 1 V p3p2p1p0c0 $end
$var wire 4 W sum [3:0] $end
$var wire 4 X c [3:0] $end
$upscope $end
$scope module c3 $end
$var wire 4 Y A [3:0] $end
$var wire 4 Z B [3:0] $end
$var wire 1 [ C2L $end
$var wire 1 \ Cin $end
$var wire 1 ] carry $end
$var wire 4 ^ g [3:0] $end
$var wire 4 _ p [3:0] $end
$var wire 1 ` p0c0 $end
$var wire 1 a p1g0 $end
$var wire 1 b p1p0c0 $end
$var wire 1 c p2g1 $end
$var wire 1 d p2p1g0 $end
$var wire 1 e p2p1p0c0 $end
$var wire 1 f p3g2 $end
$var wire 1 g p3p2g1 $end
$var wire 1 h p3p2p1g0 $end
$var wire 1 i p3p2p1p0c0 $end
$var wire 4 j sum [3:0] $end
$var wire 4 k c [3:0] $end
$upscope $end
$scope module c4 $end
$var wire 4 l A [3:0] $end
$var wire 4 m B [3:0] $end
$var wire 1 n C2L $end
$var wire 1 o Cin $end
$var wire 1 p carry $end
$var wire 4 q g [3:0] $end
$var wire 4 r p [3:0] $end
$var wire 1 s p0c0 $end
$var wire 1 t p1g0 $end
$var wire 1 u p1p0c0 $end
$var wire 1 v p2g1 $end
$var wire 1 w p2p1g0 $end
$var wire 1 x p2p1p0c0 $end
$var wire 1 y p3g2 $end
$var wire 1 z p3p2g1 $end
$var wire 1 { p3p2p1g0 $end
$var wire 1 | p3p2p1p0c0 $end
$var wire 4 } sum [3:0] $end
$var wire 4 ~ c [3:0] $end
$upscope $end
$upscope $end
$upscope $end
$enddefinitions $end
$comment Show the parameter values. $end
$dumpall
$end
#0
$dumpvars
b0 ~
b0 }
0|
0{
0z
0y
0x
0w
0v
0u
0t
0s
b0 r
b0 q
0p
0o
0n
b0 m
b0 l
b110 k
b100 j
0i
0h
0g
0f
0e
0d
0c
0b
1a
0`
b10 _
b1 ^
0]
0\
0[
b11 Z
b1 Y
b0 X
b110 W
0V
0U
0T
0S
0R
0Q
0P
0O
0N
0M
b110 L
b0 K
0J
0I
0H
b100 G
b10 F
b1110 E
b1000 D
0C
0B
0A
0@
0?
1>
0=
0<
1;
0:
b110 9
b1 8
07
16
b101 5
b11 4
b1 3
b0 2
b10001101000 1
10
1/
b1101000101 .
b1111110010111010 -
b1101000101 ,
b100100011 +
0*
0)
0(
0'
0&
0%
b1101000101 $
b100100011 #
0"
b10001101000 !
$end
#200
1"
1'
1)
0*
b1001 3
1n
b1000 2
1p
b1110 ~
1t
1w
1{
b1 q
b10001101000 !
b10001101000 1
b0 }
b1 m
b1110 r
b1001101000101 .
b1110110010111010 -
b1111 l
b1001101000101 $
b1001101000101 ,
b1111000100100011 #
b1111000100100011 +
#400
b1000 3
06
1:
0;
0>
b100 X
b0 k
0a
b1100 ~
0t
0w
0{
b1101 W
b1101 j
b1101 }
0"
b10 8
b1001 9
b10 K
b1001 L
b0 ^
b1101 _
b1110 q
b1 r
0'
b1010 5
b1011 G
b1100 Z
b1110 m
b1101110111011110 !
b1101110111011110 1
b1110 D
00
b1110110010111010 .
b111 E
1&
#600
0"
16
0(
0)
0*
b1 3
0n
1;
1>
b0 X
b110 k
1a
b0 2
0p
b110 W
b100 j
b0 ~
0:
b1 8
b110 9
b0 K
b110 L
b1 ^
b10 _
b0 }
b10001101000 !
b10001101000 1
b1000 D
b101 5
b100 G
b11 Z
b0 m
b0 q
b0 r
0/
10
b1110 E
b1101000101 .
b1111110010111010 -
b0 l
1%
0&
b1101000101 $
b1101000101 ,
b100100011 #
b100100011 +
#800
1"
1(
1*
b1001 3
1n
b1110 ~
b111 q
b1110010001101000 !
b1110010001101000 1
b1110 }
b111 m
b0 r
b111001101000101 .
b1000110010111010 -
b111 l
b111001101000101 $
b111001101000101 ,
b111000100100011 #
b111000100100011 +
#1000
0"
0(
1)
0*
b1000 2
1p
0y
b1111 q
b1110010001101000 !
b1110010001101000 1
b1110 }
b1111 m
b0 r
b1111001101000101 .
b110010111010 -
b1111 l
b1111001101000101 $
b1111001101000101 ,
b1111000100100011 #
b1111000100100011 +
#1200
1"
1(
1*
b1 3
0n
b100 ~
0v
b100010001101000 !
b100010001101000 1
b100 }
b1010 m
b1010 q
b0 r
b1010001101000101 .
b101110010111010 -
b1010 l
b1010001101000101 $
b1010001101000101 ,
b1010000100100011 #
b1010000100100011 +
#1400
0"
0(
0*
b1001 3
1n
1t
1w
1{
b1110 ~
0v
b1 q
b10001101000 !
b10001101000 1
b0 }
b1 m
b1110 r
b1001101000101 .
b1110110010111010 -
b1111 l
b1001101000101 $
b1001101000101 ,
b1111000100100011 #
b1111000100100011 +
#1600
0"
0(
06
0)
0*
b0 3
0n
b0 2
0p
1:
0;
0>
b100 X
b0 k
0a
b1101 W
b1101 j
b0 ~
0t
0w
0{
b10 8
b1001 9
b10 K
b1001 L
b0 ^
b1101 _
b10 }
b10110111011110 !
b10110111011110 1
b1110 D
b1010 5
b1011 G
b1100 Z
b0 m
b0 q
b10 r
00
b111 E
b110010111010 .
b110010111010 -
b10 l
1&
b1111001101000101 $
b1111001101000101 ,
b10000100100011 #
b10000100100011 +
#1800
1"
1(
1*
b1000 3
1n
1t
b1110 ~
b101 q
b1100110111011110 !
b1100110111011110 1
b1100 }
b101 m
b10 r
b101110010111010 .
b101110010111010 -
b111 l
b1010001101000101 $
b1010001101000101 ,
b111000100100011 #
b111000100100011 +
