Lab3/Multiplexer.v
`timescale 1ns/100ps

module MUX (
    output wire res, 
    input wire  sel, s0, s1
);
    not (selbar, sel);
    and (t0, s0, selbar);
    and (t1, s1, sel);
    or (res, t0, t1);
endmodule

module MUX4 (
    output wire res,
    input wire [1:0] sel,
    input wire [3:0] in
);
    MUX m1(ans1, sel[0], in[0], in[1]);
    MUX m2(ans2, sel[0], in[2], in[3]);
    MUX m3(res, sel[1], ans1, ans2);
endmodule

module MUX8 (
    output wire res,
    input wire [2:0] sel,
    input wire [7:0] in 
);
    MUX4 m1(ans1, sel[1:0], in[3:0]);
    MUX4 m2(ans2, sel[1:0], in[7:4]);
    MUX m3(res, sel[2], ans1, ans2);
endmodule

Verilog/Lab3/MUX_tb.v
`timescale 1ns/100ps

module MUX_tb();

	reg[7:0] inp;
    reg[2:0] sel;
	wire result;

    MUX8 M(result, sel, inp);
	
	initial begin
		
		inp = 8'b11101010;
		sel = 3'b000;

		$dumpfile("MUX_tb.vcd");
		$dumpvars(0, MUX_tb);
        #161
        $finish;
		
	end

    always begin
            
            #20
		    $display("inp = %b, sel = %b, result = %b", inp, sel, result);
			sel = sel+1;

    end

endmodule

Verilog/Lab3/MUX_tb.vcd
$date
	Mon Feb 20 00:52:56 2023
$end
$version
	Icarus Verilog
$end
$timescale
	100ps
$end
$scope module MUX_tb $end
$var wire 1 ! result $end
$var reg 8 " inp [7:0] $end
$var reg 3 # sel [2:0] $end
$scope module M $end
$var wire 8 $ in [7:0] $end
$var wire 3 % sel [2:0] $end
$var wire 1 ! res $end
$var wire 1 & ans2 $end
$var wire 1 ' ans1 $end
$scope module m1 $end
$var wire 4 ( in [3:0] $end
$var wire 2 ) sel [1:0] $end
$var wire 1 ' res $end
$var wire 1 * ans2 $end
$var wire 1 + ans1 $end
$scope module m1 $end
$var wire 1 + res $end
$var wire 1 , s0 $end
$var wire 1 - s1 $end
$var wire 1 . sel $end
$var wire 1 / selbar $end
$var wire 1 0 t0 $end
$var wire 1 1 t1 $end
$upscope $end
$scope module m2 $end
$var wire 1 * res $end
$var wire 1 2 s0 $end
$var wire 1 3 s1 $end
$var wire 1 4 sel $end
$var wire 1 5 selbar $end
$var wire 1 6 t0 $end
$var wire 1 7 t1 $end
$upscope $end
$scope module m3 $end
$var wire 1 ' res $end
$var wire 1 + s0 $end
$var wire 1 * s1 $end
$var wire 1 8 sel $end
$var wire 1 9 selbar $end
$var wire 1 : t0 $end
$var wire 1 ; t1 $end
$upscope $end
$upscope $end
$scope module m2 $end
$var wire 4 < in [3:0] $end
$var wire 2 = sel [1:0] $end
$var wire 1 & res $end
$var wire 1 > ans2 $end
$var wire 1 ? ans1 $end
$scope module m1 $end
$var wire 1 ? res $end
$var wire 1 @ s0 $end
$var wire 1 A s1 $end
$var wire 1 B sel $end
$var wire 1 C selbar $end
$var wire 1 D t0 $end
$var wire 1 E t1 $end
$upscope $end
$scope module m2 $end
$var wire 1 > res $end
$var wire 1 F s0 $end
$var wire 1 G s1 $end
$var wire 1 H sel $end
$var wire 1 I selbar $end
$var wire 1 J t0 $end
$var wire 1 K t1 $end
$upscope $end
$scope module m3 $end
$var wire 1 & res $end
$var wire 1 ? s0 $end
$var wire 1 > s1 $end
$var wire 1 L sel $end
$var wire 1 M selbar $end
$var wire 1 N t0 $end
$var wire 1 O t1 $end
$upscope $end
$upscope $end
$scope module m3 $end
$var wire 1 ! res $end
$var wire 1 ' s0 $end
$var wire 1 & s1 $end
$var wire 1 P sel $end
$var wire 1 Q selbar $end
$var wire 1 R t0 $end
$var wire 1 S t1 $end
$upscope $end
$upscope $end
$upscope $end
$enddefinitions $end
$comment Show the parameter values. $end
$dumpall
$end
#0
$dumpvars
0S
0R
1Q
0P
0O
0N
1M
0L
0K
1J
1I
0H
1G
1F
0E
0D
1C
0B
1A
0@
0?
1>
b0 =
b1110 <
0;
0:
19
08
07
06
15
04
13
02
01
00
1/
0.
1-
0,
0+
0*
b0 )
b1010 (
0'
0&
b0 %
b11101010 $
b0 #
b11101010 "
0!
$end
#200
1!
1R
1'
1&
1:
1N
1+
1*
1?
0J
0/
11
05
17
0C
1E
0I
1K
1.
14
1B
1H
b1 )
b1 =
b1 #
b1 %
#400
0!
0R
0'
1&
0+
0*
0:
0?
1J
1>
0N
1/
01
15
07
09
0;
1C
0E
1I
0K
0M
1O
0.
04
18
0B
0H
1L
b10 )
b10 =
b10 #
b10 %
#600
1!
1R
1'
1;
1+
1*
1?
0J
0/
11
05
17
0C
1E
0I
1K
1.
14
1B
1H
b11 )
b11 =
b11 #
b11 %
#800
0!
0+
0*
0:
0'
0?
1J
1>
0N
0&
1/
01
15
07
19
0;
1C
0E
1I
0K
1M
0O
0R
0.
04
08
0B
0H
0L
0Q
0S
b0 )
b0 =
1P
b100 #
b100 %
#1000
1!
1S
1'
1&
1:
1N
1+
1*
1?
0J
0/
11
05
17
0C
1E
0I
1K
1.
14
1B
1H
b1 )
b1 =
b101 #
b101 %
#1200
1!
1S
0'
1&
0+
0*
0:
0?
1J
1>
0N
1/
01
15
07
09
0;
1C
0E
1I
0K
0M
1O
0.
04
18
0B
0H
1L
b10 )
b10 =
b110 #
b110 %
#1400
1'
1;
1+
1*
1?
0J
0/
11
05
17
0C
1E
0I
1K
1.
14
1B
1H
b11 )
b11 =
b111 #
b111 %
#1600
0+
0*
0:
0'
0?
1J
1>
0N
0&
1/
01
15
07
19
0;
1C
0E
1I
0K
1M
0O
0R
0!
0.
04
08
0B
0H
0L
1Q
0S
b0 )
b0 =
0P
b0 #
b0 %
