Lab1/CLA.v
`timescale 1ns/1ns

module CLA(sum,carry,C2L,A,B,Cin); 
	input wire [3:0]A;
	input wire [3:0]B;
	input wire Cin;
	output wire[3:0]sum;
	output carry;
	output C2L;

	wire [3:0]p;
	wire [3:0]g;
	and And[3:0](g[3:0],A[3:0],B[3:0]);
	xor Xor[3:0](p[3:0],A[3:0],B[3:0]);
	
	
	wire[3:0]c;
	
	buf(c[0],Cin);
	and(p0c0,p[0],c[0]);
	or(c[1],p0c0,g[0]);
	
	and(p1p0c0,p[1],p[0],c[0]);
	and(p1g0,p[1],g[0]);
	or(c[2],p1p0c0,p1g0,g[1]);
	
	and(p2p1p0c0,p[2],p[1],p[0],c[0]);
	and(p2p1g0,p[2],p[1],g[0]);
	and(p2g1,p[2],g[1]);
	or(c[3],p2p1p0c0,p2p1g0,p2g1,g[2]);
	
	buf(C2L,c[3]);
	
	and(p3p2p1p0c0,p[3],p[2],p[1],p[0],c[0]);
	and(p3p2p1g0,p[3],p[2],p[1],g[0]);
	and(p3p2g1,p[3],p[2],g[1]);
	and(p3g2,p[3],g[2]);
	or(carry,p3p2p1p0c0,p3p2p1g0,p3p2g1,p3g2,g[3]);
	
	xor XOR[3:0](sum,p,c);
	
endmodule


module CLA16_higher(sum,overF,A,B,sub,sign);
	input wire [15:0] A;
	input wire [15:0] B;
	input sub;
	input sign;
	output wire [15:0] sum;
	output overF;
	
	wire[15:0] op3;

	xor XOR_op[15:0](op3,B,sub);
	wire[3:0] carry;
	wire Cin;
	buf(Cin,sub);
	wire[15:0] p;
	wire[15:0] g;
	and And[15:0](g[15:0],A[15:0],op3[15:0]);
	xor XOR[15:0](p[15:0],A[15:0],op3[15:0]);
	
	and(p0I,p[3],p[2],p[1],p[0]);
	and(p1I,p[7],p[6],p[5],p[4]);
	and(p2I,p[11],p[10],p[9],p[8]);
	and(p3I,p[15],p[14],p[13],p[12]);
	
	and(p3p2p1g0,p[3],p[2],p[1],g[0]);
	and(p3p2g1,p[3],p[2],g[1]);
	and(p3g2,p[3],g[2]);
	and(g0I,p3p2p1g0,p3p2g1,p3g2,g[3]);
	
	and(p7p6p5g4,p[7],p[6],p[5],g[4]);
	and(p7p6g5,p[7],p[6],g[5]);
	and(p7g6,p[7],g[6]);
	and(g1I,p7p6p5g4,p7p6g5,p7g6,g[7]);
	
	and(p11p10p9g8,p[11],p[10],p[9],g[8]);
	and(p11p10g9,p[11],p[10],g[9]);
	and(p11g10,p[11],g[10]);
	and(g2I,p11p10p9g8,p11p10g9,p11g10,g[11]);
	
	and(p15p14p13g12,p[15],p[14],p[13],g[12]);
	and(p15p14g13,p[15],p[14],g[13]);
	and(p15g14,p[15],g[14]);
	and(g3I,p15p14p13g12,p15p14g13,p15g14,g[15]);

	and(p0Ic0,p0I,Cin);
	or(carry[0],p0Ic0,g0I);
	
	and(p1Ip0Ic0,p1I,p0I,Cin);
	and(p1Ig0I,p1I,g0I);
	or(carry[1],p1Ip0Ic0,p1Ig0I,g1I);
	
	and(p2Ip1Ip0Ic0,p2I,p1I,p0I,Cin);
	and(p2Ip1Ig0I,p2I,p1I,g0I);
	and(p2Ig1I,p2I,g1I);
	or(carry[2],p2Ip1Ip0Ic0,p2Ip1Ig0I,p2Ig1I,g2I);
	
	and(p3Ip2Ip1Ip0Ic0,p3I,p2I,p1I,p0I,Cin);
	and(p3Ip2Ip1Ig0I,p3I,p2I,p1I,g0I);
	and(p3Ip2Ig1I,p3I,p2I,g1I);
	and(p3Ig2I,p3I,g2I);
	or(carry[3],p3Ip2Ip1Ip0Ic0,p3Ip2Ip1Ig0I,p3Ip2Ig1I,p3Ig2I,g3I);
	
	wire carry2[3:0];
	wire carry2L[3:0];
	
	CLA cla1(sum[3:0],carry2[0],carry2L[0],A[3:0],op3[3:0],Cin);
	CLA cla2(sum[7:4],carry2[1],carry2L[1],A[7:4],op3[7:4],carry[0]);
	CLA cla3(sum[11:8],carry2[2],carry2L[2],A[11:8],op3[11:8],carry[1]);
	CLA cla4(sum[15:12],carry2[3],carry2L[3],A[15:12],op3[15:12],carry[2]);
	
	/*
	xor(check,carry[3],carry2[3]);
	xor XOR1(equal,carry2[3],carry2L[3]);
	not NOT3(equalC,equal);
	not NOT1(sign_bar,sign);
	not NOT2(sub_bar,sub);
	and And1(mint1,sign_bar,sub_bar);
	or OR1(mint2,sign,sub);
	
	and AND2(mint3,mint1,carry2[3]);
	and AND3(mint4,mint2,equalC);
	
	or ORF(overF,mint3,mint4);
	*/
	
	// wire o1,o2;
    // wire x1,x2;
    // wire last_bar, c2l_bar;
    // not Nott1(last_bar, carry2[3]);
    // not Nott2(c2l_bar, carry2L[3]);

    
    // buf Buf1 (o1,carry2[3]);
    // xor Xor1 (o2, carry2[3], carry2L[3]);

    // wire sign_bar;
    // not Not1 (sign_bar, sign); 

    // wire mint1, mint2;
    // and And1 (mint1, sign_bar, o1);
    // and And2 (mint2, sign,  o2);

    // or Or3 (overF, mint1, mint2);

	
    wire o1,o2;
    wire x1,x2;
    wire last_bar, c2l_bar;
    not Nott1(last_bar, carry[3]);
    not Nott2(c2l_bar, carry2L[3]);

    
    buf Buf1 (o1,carry2[3]);
    xor Xor1 (o2, carry2[3], carry2L[3]);

    wire sign_bar;
    not Not1 (sign_bar, sign); 

    wire mint1, mint2;
    and And1 (mint1, sign_bar, o1);
    and And2 (mint2, sign,  o2);

    or Or (overF, mint1, mint2);

endmodule

Lab1/CLA16_Higher_tb.v
`timescale 1ns/100ps

module CLA16_tb ();
    
    reg [15:0] A, B;
    reg subtract;   //  equals 1 for subtraction
    reg sign;       // equals 1 for signed
    wire [15:0] res;
    wire ovflow;

    CLA16_higher _C (res, ovflow, A, B, subtract, sign);

    initial begin

        // unsigned case 1 no carry
        $display("unsigned case 1 no carry");
        A = 16'h0123;
        B = 16'h0345;
        subtract = 0;
        sign = 0;

        $dumpfile("CLA16_tb.vcd");
        $dumpvars(0, CLA16_tb);

        #20
        $display("A = %x, B = %x, RESULT = %x, OvFlow = %b", A, B, res, ovflow);
        $display("Ans should be RESULT = 0468, OvFlow = 0\n");


        // unsigned case 2 carry
        $display("unsigned case 2 carry");
        A = 16'hF123;
        B = 16'h1345;
        subtract = 0;
        sign = 0;
        #20
        $display("A = %x, B = %x, RESULT = %x, OvFlow = %b", A, B, res, ovflow);
        $display("Ans should be RESULT = 0468, OvFlow = 1\n");

        // unsigned case 3 subtraction
        $display("unsigned case 3 subtraction");
        A = 16'hF123;
        B = 16'h1345;
        subtract = 1;
        sign = 0;
        #20
        $display("A = %x, B = %x, RESULT = %x, OvFlow = %b", A, B, res, ovflow);
        $display("Ans should be RESULT = DDDE, OvFlow = 0\n");

        // signed case 1 no overflow, positive
        $display("signed case 1 no overflow, positive");
        A = 16'h0123;
        B = 16'h0345;
        subtract = 0;
        sign = 1;
        #20
        $display("A = %x, B = %x, RESULT = %x, OvFlow = %b", A, B, res, ovflow);
        $display("Ans should be RESULT = 0468, OvFlow = 0\n");

        // signed case 2  overflow, positive
        $display("signed case 2  overflow, positive");
        A = 16'h7123;
        B = 16'h7345;
        subtract = 0;
        sign = 1;
        #20
        $display("A = %x, B = %x, RESULT = %x, OvFlow = %b", A, B, res, ovflow);
        $display("Ans should be RESULT = E468, OvFlow = 0\n");

        // signed case 3 no overflow, negative
        $display("signed case 3 no overflow, negative");
        A = 16'hF123;
        B = 16'hF345;
        subtract = 0;
        sign = 1;
        #20
        $display("A = %x, B = %x, RESULT = %x, OvFlow = %b", A, B, res, ovflow);
        $display("Ans should be RESULT = E468, OvFlow = 0\n");

        // signed case 4 overflow, negative
        A = 16'hA123;
        B = 16'hA345;
        subtract = 0;
        sign = 1;
        #20
        $display("A = %x, B = %x, RESULT = %x, OvFlow = %b", A, B, res, ovflow);
        $display("Ans should be RESULT = 4468, OvFlow = 1\n");

        // signed case 5 addition of opposite signs
        A = 16'hF123;
        B = 16'h1345;
        subtract = 0;
        sign = 1;
        #20
        $display("A = %x, B = %x, RESULT = %x, OvFlow = %b", A, B, res, ovflow);
        $display("Ans should be RESULT = 0468, OvFlow = 0\n");

        // signed case 6 subtraction of opposite signs without overflow
        A = 16'h2123;
        B = 16'hF345;
        subtract = 1;
        sign = 1;
        #20
        $display("A = %x, B = %x, RESULT = %x, OvFlow = %b\n", A, B, res, ovflow);
        $display("Ans should be RESULT = 2DDE, OvFlow = 0\n");

        // signed case 7 subtraction of opposite signs with overflow
        A = 16'h7123;
        B = 16'hA345;
        subtract = 1;
        sign = 1;
        #20
        $display("A = %x, B = %x, RESULT = %x, OvFlow = %b\n", A, B, res, ovflow);
        $display("Ans should be RESULT = CDDE, OvFlow = 1\n");

    end

endmodule

Lab1/CLA16_tb.vcd
$date
	Mon Feb 06 17:10:41 2023
$end
$version
	Icarus Verilog
$end
$timescale
	100ps
$end
$scope module CLA16_tb $end
$var wire 16 ! res [15:0] $end
$var wire 1 " ovflow $end
$var reg 16 # A [15:0] $end
$var reg 16 $ B [15:0] $end
$var reg 1 % sign $end
$var reg 1 & subtract $end
$scope module _C $end
$var wire 16 ' A [15:0] $end
$var wire 16 ( B [15:0] $end
$var wire 1 ) Cin $end
$var wire 1 * c2l_bar $end
$var wire 16 + g [15:0] $end
$var wire 1 , g0I $end
$var wire 1 - g1I $end
$var wire 1 . g2I $end
$var wire 1 / g3I $end
$var wire 1 0 last_bar $end
$var wire 1 1 mint1 $end
$var wire 1 2 mint2 $end
$var wire 1 3 o1 $end
$var wire 1 4 o2 $end
$var wire 16 5 op3 [15:0] $end
$var wire 1 " overF $end
$var wire 16 6 p [15:0] $end
$var wire 1 7 p0I $end
$var wire 1 8 p0Ic0 $end
$var wire 1 9 p11g10 $end
$var wire 1 : p11p10g9 $end
$var wire 1 ; p11p10p9g8 $end
$var wire 1 < p15g14 $end
$var wire 1 = p15p14g13 $end
$var wire 1 > p15p14p13g12 $end
$var wire 1 ? p1I $end
$var wire 1 @ p1Ig0I $end
$var wire 1 A p1Ip0Ic0 $end
$var wire 1 B p2I $end
$var wire 1 C p2Ig1I $end
$var wire 1 D p2Ip1Ig0I $end
$var wire 1 E p2Ip1Ip0Ic0 $end
$var wire 1 F p3I $end
$var wire 1 G p3Ig2I $end
$var wire 1 H p3Ip2Ig1I $end
$var wire 1 I p3Ip2Ip1Ig0I $end
$var wire 1 J p3Ip2Ip1Ip0Ic0 $end
$var wire 1 K p3g2 $end
$var wire 1 L p3p2g1 $end
$var wire 1 M p3p2p1g0 $end
$var wire 1 N p7g6 $end
$var wire 1 O p7p6g5 $end
$var wire 1 P p7p6p5g4 $end
$var wire 1 % sign $end
$var wire 1 Q sign_bar $end
$var wire 1 & sub $end
$var wire 16 R sum [15:0] $end
$var wire 4 S carry [3:0] $end
$scope module cla1 $end
$var wire 4 T A [3:0] $end
$var wire 4 U B [3:0] $end
$var wire 1 V C2L $end
$var wire 1 ) Cin $end
$var wire 1 W carry $end
$var wire 4 X g [3:0] $end
$var wire 4 Y p [3:0] $end
$var wire 1 Z p0c0 $end
$var wire 1 [ p1g0 $end
$var wire 1 \ p1p0c0 $end
$var wire 1 ] p2g1 $end
$var wire 1 ^ p2p1g0 $end
$var wire 1 _ p2p1p0c0 $end
$var wire 1 ` p3g2 $end
$var wire 1 a p3p2g1 $end
$var wire 1 b p3p2p1g0 $end
$var wire 1 c p3p2p1p0c0 $end
$var wire 4 d sum [3:0] $end
$var wire 4 e c [3:0] $end
$upscope $end
$scope module cla2 $end
$var wire 4 f A [3:0] $end
$var wire 4 g B [3:0] $end
$var wire 1 h C2L $end
$var wire 1 i Cin $end
$var wire 1 j carry $end
$var wire 4 k g [3:0] $end
$var wire 4 l p [3:0] $end
$var wire 1 m p0c0 $end
$var wire 1 n p1g0 $end
$var wire 1 o p1p0c0 $end
$var wire 1 p p2g1 $end
$var wire 1 q p2p1g0 $end
$var wire 1 r p2p1p0c0 $end
$var wire 1 s p3g2 $end
$var wire 1 t p3p2g1 $end
$var wire 1 u p3p2p1g0 $end
$var wire 1 v p3p2p1p0c0 $end
$var wire 4 w sum [3:0] $end
$var wire 4 x c [3:0] $end
$upscope $end
$scope module cla3 $end
$var wire 4 y A [3:0] $end
$var wire 4 z B [3:0] $end
$var wire 1 { C2L $end
$var wire 1 | Cin $end
$var wire 1 } carry $end
$var wire 4 ~ g [3:0] $end
$var wire 4 !" p [3:0] $end
$var wire 1 "" p0c0 $end
$var wire 1 #" p1g0 $end
$var wire 1 $" p1p0c0 $end
$var wire 1 %" p2g1 $end
$var wire 1 &" p2p1g0 $end
$var wire 1 '" p2p1p0c0 $end
$var wire 1 (" p3g2 $end
$var wire 1 )" p3p2g1 $end
$var wire 1 *" p3p2p1g0 $end
$var wire 1 +" p3p2p1p0c0 $end
$var wire 4 ," sum [3:0] $end
$var wire 4 -" c [3:0] $end
$upscope $end
$scope module cla4 $end
$var wire 4 ." A [3:0] $end
$var wire 4 /" B [3:0] $end
$var wire 1 0" C2L $end
$var wire 1 1" Cin $end
$var wire 1 2" carry $end
$var wire 4 3" g [3:0] $end
$var wire 4 4" p [3:0] $end
$var wire 1 5" p0c0 $end
$var wire 1 6" p1g0 $end
$var wire 1 7" p1p0c0 $end
$var wire 1 8" p2g1 $end
$var wire 1 9" p2p1g0 $end
$var wire 1 :" p2p1p0c0 $end
$var wire 1 ;" p3g2 $end
$var wire 1 <" p3p2g1 $end
$var wire 1 =" p3p2p1g0 $end
$var wire 1 >" p3p2p1p0c0 $end
$var wire 4 ?" sum [3:0] $end
$var wire 4 @" c [3:0] $end
$upscope $end
$upscope $end
$upscope $end
$enddefinitions $end
$comment Show the parameter values. $end
$dumpall
$end
#0
$dumpvars
b0 @"
b0 ?"
0>"
0="
0<"
0;"
0:"
09"
08"
07"
06"
05"
b0 4"
b0 3"
02"
01"
00"
b0 /"
b0 ."
b110 -"
b100 ,"
0+"
0*"
0)"
0("
0'"
0&"
0%"
0$"
1#"
0""
b10 !"
b1 ~
0}
0|
0{
b11 z
b1 y
b0 x
b110 w
0v
0u
0t
0s
0r
0q
0p
0o
0n
0m
b110 l
b0 k
0j
0i
0h
b100 g
b10 f
b1110 e
b1000 d
0c
0b
0a
0`
0_
1^
0]
0\
1[
0Z
b110 Y
b1 X
0W
1V
b101 U
b11 T
b0 S
b10001101000 R
1Q
0P
0O
0N
0M
0L
0K
0J
0I
0H
0G
0F
0E
0D
0C
0B
0A
0@
0?
0>
0=
0<
0;
0:
09
08
07
b1001100110 6
b1101000101 5
04
03
02
01
10
0/
0.
0-
0,
b100000001 +
1*
0)
b1101000101 (
b100100011 '
0&
0%
b1101000101 $
b100100011 #
0"
b10001101000 !
$end
#200
1"
0*
11
10"
04
13
12"
b1110 @"
16"
19"
1="
1>
b1 3"
0F
b10001101000 !
b10001101000 R
b0 ?"
b1000100000001 +
b1 /"
b1110 4"
b1001101000101 5
b1110001001100110 6
b1111 ."
b1001101000101 $
b1001101000101 (
b1111000100100011 #
b1111000100100011 '
#400
0V
0[
0^
b100 x
b0 -"
0#"
b1100 @"
06"
09"
0="
1Z
0>
b1101 w
b1101 ,"
b1101 ?"
b1101110111011110 !
b1101110111011110 R
b1110 d
b10 X
b1001 Y
b10 k
b1001 l
b0 ~
b1101 !"
b1110 3"
b1 4"
b111 e
b1110000000100010 +
b1110110011001 6
b1010 U
b1011 g
b1100 z
b1110 /"
1)
b1110110010111010 5
1&
#600
1V
1*
02
00"
04
03
1[
1^
b0 x
b110 -"
1#"
02"
0Z
b110 w
b100 ,"
b0 @"
0"
b1000 d
b1 X
b110 Y
b0 k
b110 l
b1 ~
b10 !"
b10001101000 !
b10001101000 R
b0 ?"
01
b1110 e
b101 U
b100 g
b11 z
b0 /"
b0 3"
b0 4"
0Q
0)
b1101000101 5
b100000001 +
b1001100110 6
b0 ."
1%
0&
b1101000101 $
b1101000101 (
b100100011 #
b100100011 '
#800
1"
12
14
0*
10"
b1110 @"
b111 3"
b1110010001101000 !
b1110010001101000 R
b1110 ?"
b111000100000001 +
b111 /"
b0 4"
b111001101000101 5
b1001100110 6
b111 ."
b111001101000101 $
b111001101000101 (
b111000100100011 #
b111000100100011 '
#1000
0"
02
04
13
12"
0;"
b1111 3"
0<
b1110010001101000 !
b1110010001101000 R
b1110 ?"
b1111000100000001 +
b1111 /"
b0 4"
b1111001101000101 5
b1001100110 6
b1111 ."
b1111001101000101 $
b1111001101000101 (
b1111000100100011 #
b1111000100100011 '
#1200
1"
12
14
1*
00"
b100 @"
08"
b100010001101000 !
b100010001101000 R
b100 ?"
b1010 /"
b1010 3"
b0 4"
b1010001101000101 5
b1010000100000001 +
b1001100110 6
b1010 ."
b1010001101000101 $
b1010001101000101 (
b1010000100100011 #
b1010000100100011 '
#1400
0"
02
04
0*
10"
16"
19"
1="
b1110 @"
1>
08"
b1 3"
b10001101000 !
b10001101000 R
b0 ?"
b1000100000001 +
b1 /"
b1110 4"
b1001101000101 5
b1110001001100110 6
b1111 ."
b1001101000101 $
b1001101000101 (
b1111000100100011 #
b1111000100100011 '
#1600
0"
0V
1*
02
00"
04
03
02"
0[
0^
b100 x
b0 -"
0#"
1Z
b1101 w
b1101 ,"
b0 @"
06"
09"
0="
b1110 d
b10 X
b1001 Y
b10 k
b1001 l
b0 ~
b1101 !"
0>
b10110111011110 !
b10110111011110 R
b10 ?"
b111 e
b1010 U
b1011 g
b1100 z
b0 /"
b0 3"
b10 4"
1)
b110010111010 5
b100010 +
b10110110011001 6
b10 ."
1&
b1111001101000101 $
b1111001101000101 (
b10000100100011 #
b10000100100011 '
#1800
1"
12
14
0*
10"
16"
b1110 @"
b101 3"
b1100110111011110 !
b1100110111011110 R
b1100 ?"
b101000000100010 +
b101 /"
b10 4"
b101110010111010 5
b10110110011001 6
b111 ."
b1010001101000101 $
b1010001101000101 (
b111000100100011 #
b111000100100011 '
